Metadata-Version: 2.4
Name: hack4u_m4xwellov
Version: 0.1.1
Summary: Una biblioteca para consultar cursos de hack4u.
Home-page: https://hack4u.io
Author: m4xwellov
Dynamic: author
Dynamic: description
Dynamic: description-content-type
Dynamic: home-page
Dynamic: summary
